xhorizon/__init__.py
xhorizon/diagram_tools/__init__.py
xhorizon/diagram_tools/block_fill.py
xhorizon/diagram_tools/block_masks.py
xhorizon/diagram_tools/coord_transf.py
xhorizon/diagram_tools/curve_class.py
xhorizon/diagram_tools/curvemakers.py
xhorizon/diagram_tools/diagram_classes.py
xhorizon/diagram_tools/plotstyle.py
xhorizon/diagram_tools/region_factory.py
xhorizon/evap/__init__.py
xhorizon/evap/demo.py
xhorizon/evap/demo_AdS.py
xhorizon/evap/demo_dS.py
xhorizon/evap/demo_zoom.py
xhorizon/evap/draw.py
xhorizon/evap/draw_dS.py
xhorizon/evap/evap.py
xhorizon/evap/helpers.py
xhorizon/evap/legend.py
xhorizon/evap/massplot.py
xhorizon/evap/schwarzparams.py
xhorizon/evap/tests.py
xhorizon/shell_junction/__init__.py
xhorizon/shell_junction/active_slice_class.py
xhorizon/shell_junction/helpers.py
xhorizon/shell_junction/interpolators.py
xhorizon/shell_junction/passive_slice_class.py
xhorizon/shell_junction/reg_corner_masks.py
xhorizon/shell_junction/tests.py
xhorizon/tortoise/__init__.py
xhorizon/tortoise/math_util.py
xhorizon/tortoise/metfunc_class.py
xhorizon/tortoise/metfunc_factory.py
xhorizon/tortoise/metfunc_tests.py
xhorizon/tortoise/tortoise.py
xhorizon-1.1.3.dist-info/LICENSE
xhorizon-1.1.3.dist-info/METADATA
xhorizon-1.1.3.dist-info/WHEEL
xhorizon-1.1.3.dist-info/top_level.txt
xhorizon-1.1.3.dist-info/RECORD
