Metadata-Version: 2.1
Name: xhorizon
Version: 1.1.3
Summary: A Python package for explicitly computing Penrose diagrams in general relativity.
Home-page: https://github.com/xh-diagrams/xhorizon
Author: Joseph C Schindler
Author-email: jcschindler01@gmail.com
Classifier: Programming Language :: Python :: 3
Classifier: License :: OSI Approved :: MIT License
Classifier: Operating System :: OS Independent
Requires-Python: >=3.10
License-File: LICENSE
Requires-Dist: numpy (>=1.22.3)
Requires-Dist: scipy (>=1.8.0)
Requires-Dist: matplotlib (<4.0,>=3.5.1)
